AUTHORS
CHANGELOG.txt
DESCRIPTION
LICENSE
MANIFEST.in
README.rst
setup.py
booking/__init__.py
booking/admin.py
booking/auth_backends.py
booking/forms.py
booking/models.py
booking/urls.py
booking/utils.py
booking/views.py
booking/migrations/0001_initial.py
booking/migrations/0002_auto__chg_field_booking_booking_status.py
booking/migrations/0003_auto__add_field_booking_time_period__add_field_booking_time_unit.py
booking/migrations/0004_auto__add_field_bookingitem_subtotal__add_field_booking_total__add_fie.py
booking/migrations/0005_auto__add_bookingerror.py
booking/migrations/0006_rename_bookingstatustranslation.py
booking/migrations/0007_auto__add_bookingstatustranslation__add_unique_bookingstatustranslatio.py
booking/migrations/0008_move_data_from_old_model_to_hvad.py
booking/migrations/0009_auto__del_bookingstatustranslationrenamed.py
booking/migrations/0010_auto__chg_field_bookingitem_subtotal__chg_field_booking_total.py
booking/migrations/__init__.py
booking/templates/booking/booking_detail.html
booking/templates/booking/booking_form.html
booking/templates/booking/booking_list.html
booking/tests/__init__.py
booking/tests/factories.py
booking/tests/forms_tests.py
booking/tests/models_tests.py
booking/tests/runtests.py
booking/tests/south_settings.py
booking/tests/test_settings.py
booking/tests/urls.py
booking/tests/views_tests.py
booking/tests/test_app/__init__.py
booking/tests/test_app/models.py
booking/tests/test_app/templates/400.html
booking/tests/test_app/templates/500.html
booking/tests/test_app/templates/base.html
django_booking.egg-info/PKG-INFO
django_booking.egg-info/SOURCES.txt
django_booking.egg-info/dependency_links.txt
django_booking.egg-info/requires.txt
django_booking.egg-info/top_level.txt