Metadata-Version: 1.0
Name: django-booking
Version: 0.7.1
Summary: A reusable Django app that manages bookings for various purposes.
